{
  "dependencies": {
    "com.vrchat.base": {
      "version": "3.7.5"
    },
    "com.vrchat.avatars": {
      "version": "3.7.5"
    },
    "com.vrchat.core.vpm-resolver": {
      "version": "0.1.29"
    },
    "vrchat.blackstartx.gesture-manager": {
      "version": "3.9.3"
    },
    "jp.lilxyzw.liltoon": {
      "version": "1.8.5"
    },
    "jp.lilxyzw.lilycalinventory": {
      "version": "1.4.5"
    },
    "nadena.dev.modular-avatar": {
      "version": "1.11.1"
    },
    "com.aoyon.module-creator": {
      "version": "0.4.3"
    },
    "io.github.azukimochi.light-limit-changer": {
      "version": "1.14.3"
    }
  },
  "locked": {
    "com.vrchat.base": {
      "version": "3.7.5",
      "dependencies": {}
    },
    "com.vrchat.avatars": {
      "version": "3.7.5",
      "dependencies": {
        "com.vrchat.base": "3.7.5"
      }
    },
    "com.vrchat.core.vpm-resolver": {
      "version": "0.1.29",
      "dependencies": {}
    },
    "vrchat.blackstartx.gesture-manager": {
      "version": "3.9.3",
      "dependencies": {
        "com.vrchat.avatars": ">=3.5.2 < 3.8.X"
      }
    },
    "jp.lilxyzw.liltoon": {
      "version": "1.8.5",
      "dependencies": {}
    },
    "jp.lilxyzw.lilycalinventory": {
      "version": "1.4.5",
      "dependencies": {}
    },
    "nadena.dev.modular-avatar": {
      "version": "1.11.1",
      "dependencies": {
        "com.vrchat.avatars": ">=3.7.4",
        "nadena.dev.ndmf": ">=1.6.0 <2.0.0-a"
      }
    },
    "nadena.dev.ndmf": {
      "version": "1.6.2",
      "dependencies": {}
    },
    "com.aoyon.module-creator": {
      "version": "0.4.3",
      "dependencies": {
        "com.vrchat.avatars": ">=3.0.0"
      }
    },
    "io.github.azukimochi.light-limit-changer": {
      "version": "1.14.3",
      "dependencies": {
        "com.vrchat.avatars": ">=3.2.0",
        "nadena.dev.modular-avatar": "^1.9.9",
        "nadena.dev.ndmf": "^1.4.0"
      }
    }
  }
}